ctof/__init__.py
ctof/convert.py
ctof/version.py
ctof-0.2.1.dist-info/LICENSE
ctof-0.2.1.dist-info/METADATA
ctof-0.2.1.dist-info/WHEEL
ctof-0.2.1.dist-info/top_level.txt
ctof-0.2.1.dist-info/RECORD
