Metadata-Version: 2.1
Name: ctof
Version: 0.2.1
Summary: A simple library for temperature unit conversion
Home-page: UNKNOWN
Author: David Costell
Author-email: davidcostell44@gmail.com
License: MIT
Project-URL: GitHub, https://github.com/DontEatThemCookies/ctof
Platform: UNKNOWN
Classifier: Intended Audience :: Developers
Classifier: License :: OSI Approved :: MIT License
Classifier: Programming Language :: Python
Classifier: Programming Language :: Python :: 3
Classifier: Programming Language :: Python :: 3.6
Classifier: Programming Language :: Python :: 3.7
Classifier: Programming Language :: Python :: 3.8
Classifier: Programming Language :: Python :: 3.9
Classifier: Programming Language :: Python :: 3.10
Classifier: Operating System :: OS Independent
